azureml/__init__.py
azureml/_async/__init__.py
azureml/_async/async_task.py
azureml/_async/batch_task_queue.py
azureml/_async/daemon.py
azureml/_async/task_queue.py
azureml/_async/worker_pool.py
azureml/_base_sdk_common/__init__.py
azureml/_base_sdk_common/_arcadia_token_wrapper.py
azureml/_base_sdk_common/_docstring_wrapper.py
azureml/_base_sdk_common/_version.py
azureml/_base_sdk_common/abstract_run_config_element.py
azureml/_base_sdk_common/auth_utils.py
azureml/_base_sdk_common/common.py
azureml/_base_sdk_common/credentials.py
azureml/_base_sdk_common/data_transformers.py
azureml/_base_sdk_common/execution_service_address.py
azureml/_base_sdk_common/field_info.py
azureml/_base_sdk_common/merkle_tree.py
azureml/_base_sdk_common/merkle_tree_differ.py
azureml/_base_sdk_common/process_utilities.py
azureml/_base_sdk_common/project_snapshot_cache.py
azureml/_base_sdk_common/service_discovery.py
azureml/_base_sdk_common/snapshot_dto.py
azureml/_base_sdk_common/user_agent.py
azureml/_base_sdk_common/utils.py
azureml/_base_sdk_common/cli_wrapper/__init__.py
azureml/_base_sdk_common/cli_wrapper/_common.py
azureml/_base_sdk_common/cli_wrapper/cmd_computetarget.py
azureml/_base_sdk_common/cli_wrapper/cmd_computetarget_attach.py
azureml/_base_sdk_common/project/__init__.py
azureml/_base_sdk_common/project/version.py
azureml/_base_sdk_common/project/models/__init__.py
azureml/_base_sdk_common/project/models/create_project_resource_dto.py
azureml/_base_sdk_common/project/models/paginated_result_project_dto.py
azureml/_base_sdk_common/project/models/project_dto.py
azureml/_base_sdk_common/tracking/__init__.py
azureml/_base_sdk_common/tracking/git_tracking_info_provider.py
azureml/_base_sdk_common/tracking/tracking_info_provider.py
azureml/_base_sdk_common/tracking/tracking_info_registry.py
azureml/_base_sdk_common/workspace/__init__.py
azureml/_base_sdk_common/workspace/azure_machine_learning_workspaces.py
azureml/_base_sdk_common/workspace/version.py
azureml_core-1.61.0.post1.dist-info/licenses/LICENSE.txt
azureml_core-1.61.0.post1.dist-info/METADATA
azureml_core-1.61.0.post1.dist-info/WHEEL
azureml_core-1.61.0.post1.dist-info/entry_points.txt
azureml_core-1.61.0.post1.dist-info/top_level.txt
azureml_core-1.61.0.post1.dist-info/RECORD
