Metadata-Version: 2.4
Name: azureml-core
Version: 1.61.0.post1
Summary: Azure Machine Learning core packages, modules, and classes
Home-page: https://docs.microsoft.com/python/api/overview/azure/ml/?view=azure-ml-py
Author: Microsoft Corp
License: https://aka.ms/azureml-sdk-license
Classifier: Development Status :: 5 - Production/Stable
Classifier: Intended Audience :: Developers
Classifier: Intended Audience :: System Administrators
Classifier: Programming Language :: Python
Classifier: Programming Language :: Python :: 3
Classifier: Programming Language :: Python :: 3.8
Classifier: Programming Language :: Python :: 3.9
Classifier: Programming Language :: Python :: 3.10
Classifier: Programming Language :: Python :: 3.11
Requires-Python: >=3.8,< 4.0
License-File: LICENSE.txt
Requires-Dist: pytz
Requires-Dist: backports.tempfile
Requires-Dist: pathspec<1.0.0
Requires-Dist: requests[socks]<3.0.0,>=2.19.1
Requires-Dist: msal<2.0.0,>=1.15.0
Requires-Dist: msal-extensions<=2.0.0,>=0.3.0
Requires-Dist: knack<0.13.0
Requires-Dist: azure-core<2.0.0
Requires-Dist: pkginfo
Requires-Dist: argcomplete<4
Requires-Dist: humanfriendly<11.0,>=4.7
Requires-Dist: paramiko<4.0.0,>=2.0.8
Requires-Dist: azure-mgmt-resource<=24.0.0,>=15.0.0
Requires-Dist: azure-mgmt-containerregistry<15,>=8.2.0
Requires-Dist: azure-mgmt-storage<=24.0.0,>=16.0.0
Requires-Dist: azure-mgmt-keyvault<12.0.0,>=0.40.0
Requires-Dist: azure-mgmt-authorization<5,>=0.40.0
Requires-Dist: azure-mgmt-network<=30.0.0
Requires-Dist: azure-graphrbac<1.0.0,>=0.40.0
Requires-Dist: azure-common<2.0.0,>=1.1.12
Requires-Dist: msrest<=0.7.1,>=0.5.1
Requires-Dist: msrestazure<=0.7,>=0.4.33
Requires-Dist: urllib3<3.0.0,>1.26.17
Requires-Dist: packaging<26.0,>=20.0
Requires-Dist: python-dateutil<3.0.0,>=2.7.3
Requires-Dist: ndg-httpsclient<=0.5.1
Requires-Dist: SecretStorage<4.0.0
Requires-Dist: jsonpickle<5.0.0
Requires-Dist: contextlib2<22.0.0
Requires-Dist: docker<8.0.0
Requires-Dist: PyJWT<3.0.0
Requires-Dist: adal<=1.2.7,>=1.2.0
Requires-Dist: pyopenssl<26.0.0
Requires-Dist: jmespath<2.0.0
Dynamic: author
Dynamic: classifier
Dynamic: description
Dynamic: description-content-type
Dynamic: home-page
Dynamic: license
Dynamic: license-file
Dynamic: requires-dist
Dynamic: requires-python
Dynamic: summary
